pytos2/__init__.py
pytos2/py.typed
pytos2/api/__init__.py
pytos2/api/models.py
pytos2/graphql/__init__.py
pytos2/graphql/api.py
pytos2/graphql/base.py
pytos2/graphql/models.py
pytos2/models/__init__.py
pytos2/secureapp/__init__.py
pytos2/secureapp/access_requests.py
pytos2/secureapp/api.py
pytos2/secureapp/application_identities.py
pytos2/secureapp/applications.py
pytos2/secureapp/entrypoint.py
pytos2/secureapp/history.py
pytos2/secureapp/network_object.py
pytos2/secureapp/service_object.py
pytos2/securechange/__init__.py
pytos2/securechange/api.py
pytos2/securechange/designer.py
pytos2/securechange/designer_verifier_common.py
pytos2/securechange/device.py
pytos2/securechange/domain.py
pytos2/securechange/entrypoint.py
pytos2/securechange/extension.py
pytos2/securechange/network_object.py
pytos2/securechange/related_rules.py
pytos2/securechange/risk_results.py
pytos2/securechange/rule.py
pytos2/securechange/saved_search.py
pytos2/securechange/service.py
pytos2/securechange/ticket.py
pytos2/securechange/ticket_requests.py
pytos2/securechange/trigger.py
pytos2/securechange/user.py
pytos2/securechange/verifier.py
pytos2/securechange/workflow.py
pytos2/securechange/workflow_triggers.py
pytos2/securechange/fields/__init__.py
pytos2/securechange/fields/binding.py
pytos2/securechange/fields/rule_operation.py
pytos2/securetrack/__init__.py
pytos2/securetrack/api.py
pytos2/securetrack/application.py
pytos2/securetrack/change_window.py
pytos2/securetrack/cloud.py
pytos2/securetrack/device.py
pytos2/securetrack/domain.py
pytos2/securetrack/entrypoint.py
pytos2/securetrack/generic_device.py
pytos2/securetrack/generic_ignored_interface.py
pytos2/securetrack/generic_interface.py
pytos2/securetrack/generic_interface_customer.py
pytos2/securetrack/generic_route.py
pytos2/securetrack/generic_transparent_firewall.py
pytos2/securetrack/generic_vpn.py
pytos2/securetrack/interface.py
pytos2/securetrack/license.py
pytos2/securetrack/managed_devices.py
pytos2_ce-3.0.0.dist-info/licenses/LICENSE
pytos2_ce-3.0.0.dist-info/METADATA
pytos2_ce-3.0.0.dist-info/WHEEL
pytos2_ce-3.0.0.dist-info/top_level.txt
pytos2_ce-3.0.0.dist-info/RECORD
