Metadata-Version: 2.4
Name: pytos2-ce
Version: 3.0.0
Summary: Pytos2 for tos1 tos2 and beyond
Requires-Python: >=3.10
License-File: LICENSE
Requires-Dist: requests<3
Requires-Dist: traversify
Requires-Dist: attrs<25,>=24
Requires-Dist: python-json-logger<4,>=3
Requires-Dist: netaddr<2,>=1.0.0
Requires-Dist: typing_extensions
Requires-Dist: python-dateutil<3,>=2.8
Requires-Dist: requests-oauthlib
Requires-Dist: xmltodict
Provides-Extra: dev
Requires-Dist: pytest; extra == "dev"
Requires-Dist: pytest-cov; extra == "dev"
Requires-Dist: pytest-logger; extra == "dev"
Requires-Dist: responses; extra == "dev"
Requires-Dist: black; extra == "dev"
Requires-Dist: tox; extra == "dev"
Requires-Dist: ruff; extra == "dev"
Provides-Extra: dev-jupyter
Requires-Dist: black[jupyter]; extra == "dev-jupyter"
Requires-Dist: pre-commit; extra == "dev-jupyter"
Requires-Dist: nb-clean; extra == "dev-jupyter"
Dynamic: license-file
